{"post_hash": "QmctHLGpwRz2CeYYfi254oNPmy9XZtimARdVWTJme7x5MM", "parent_hash": "QmctHLGpwRz2CeYYfi254oNPmy9XZtimARdVWTJme7x5MM", "parent_type": "post", "username": "Hannibal254", "profile_pic": "https://www.redditstatic.com/avatars/defaults/v2/avatar_default_3.png", "body": "He was also very religious. He never married because no woman was pure enough for him. He contracted one woman to raise her daughter from infancy to be his bride but he called it off when she was around 14 because he saw her flirting with some boys her own age. \n\nAlso, every house around that time also had Apple Cider Vinegar which is a powerful disinfectant so that\u2019s another very popular purpose for the apples as well."}